Metadata-Version: 2.1
Name: agora-python-server-sdk-v1
Version: 0.0.3
Summary: A Python SDK for Agora Server
Home-page: https://github.com/weedge/Agora-Python-Server-SDK
Classifier: Intended Audience :: Developers
Classifier: License :: OSI Approved :: MIT License
Classifier: Topic :: Multimedia :: Sound/Audio
Classifier: Topic :: Multimedia :: Video
Classifier: Topic :: Scientific/Engineering :: Artificial Intelligence
Classifier: Programming Language :: Python :: 3.10
Classifier: Programming Language :: Python :: 3 :: Only
Requires-Python: >=3.10
